{
  "HT": "'s-Hertogenbosch",
  "HTO": "'s-Hertogenbosch Oost",
  "HDE": "'t Harde",
  "ATN": "Aalten",
  "AC": "Abcoude",
  "AKM": "Akkrum",
  "AMR": "Alkmaar",
  "AMRN": "Alkmaar Noord",
  "AML": "Almelo",
  "AMRI": "Almelo de Riet",
  "ALMB": "Almere Buiten",
  "ALM": "Almere Centrum",
  "ALMM": "Almere Muziekwijk",
  "ALMO": "Almere Oostvaarders",
  "ALMP": "Almere Parkwijk",
  "AMPO": "Almere Poort",
  "APN": "Alphen a/d Rijn",
  "AMF": "Amersfoort",
  "AMFS": "Amersfoort Schothorst",
  "AVAT": "Amersfoort Vathorst",
  "ASA": "Amsterdam Amstel",
  "ASB": "Amsterdam Bijlmer ArenA",
  "ASD": "Amsterdam Centraal",
  "ASHD": "Amsterdam Holendrecht",
  "ASDL": "Amsterdam Lelylaan",
  "ASDM": "Amsterdam Muiderpoort",
  "RAI": "Amsterdam RAI",
  "ASSP": "Amsterdam Science Park",
  "ASS": "Amsterdam Sloterdijk",
  "ASDAR": "Amsterdam Stadion",
  "ASDZ": "Amsterdam Zuid",
  "ANA": "Anna Paulowna",
  "APD": "Apeldoorn",
  "APDM": "Apeldoorn De Maten",
  "APDO": "Apeldoorn Osseveld",
  "APG": "Appingedam",
  "AKL": "Arkel",
  "ARN": "Arnemuiden",
  "AH": "Arnhem",
  "AHPR": "Arnhem Presikhaaf",
  "AHP": "Arnhem Velperpoort",
  "AHZ": "Arnhem Zuid",
  "ASN": "Assen",
  "BRN": "Baarn",
  "BF": "Baflo",
  "BRD": "Barendrecht",
  "BNC": "Barneveld Centrum",
  "BNN": "Barneveld Noord",
  "BDM": "Bedum",
  "BK": "Beek-Elsloo",
  "BSD": "Beesd",
  "BL": "Beilen",
  "BGN": "Bergen op Zoom",
  "BET": "Best",
  "BV": "Beverwijk",
  "BHV": "Bilthoven",
  "BR": "Blerick",
  "BLL": "Bloemendaal",
  "BDG": "Bodegraven",
  "BN": "Borne",
  "BSK": "Boskoop",
  "BHDV": "Boven-Hardinxveld",
  "BKF": "Bovenkarspel Flora",
  "BKG": "Bovenkarspel-Grootebroek",
  "BMR": "Boxmeer",
  "BTL": "Boxtel",
  "BD": "Breda",
  "BDPB": "Breda Prinsenbeek",
  "BKL": "Breukelen",
  "BMN": "Brummen",
  "BP": "Buitenpost",
  "BDE": "Bunde",
  "BNK": "Bunnik",
  "BSMZ": "Bussum Zuid",
  "CPS": "Capelle Schollevaar",
  "CAS": "Castricum",
  "CVM": "Chevremont",
  "CO": "Coevorden",
  "CK": "Cuijk",
  "CL": "Culemborg",
  "DA": "Daarlerveen",
  "DLN": "Dalen",
  "DL": "Dalfsen",
  "DVNK": "De Vink",
  "DEI": "Deinum",
  "DDN": "Delden",
  "DT": "Delft",
  "DTZ": "Delft Zuid",
  "DZ": "Delfzijl",
  "DZW": "Delfzijl West",
  "DLD": "Den Dolder",
  "GVC": "Den Haag Centraal",
  "GV": "Den Haag HS",
  "LAA": "Den Haag Laan v NOI",
  "GVM": "Den Haag Mariahoeve",
  "GVMW": "Den Haag Moerwijk",
  "YPB": "Den Haag Ypenburg",
  "HDR": "Den Helder",
  "HDRZ": "Den Helder Zuid",
  "DN": "Deurne",
  "DV": "Deventer",
  "DVC": "Deventer Colmschate",
  "DVT": "Deventer De Scheg",
  "DID": "Didam",
  "DMN": "Diemen",
  "DMNZ": "Diemen Zuid",
  "DR": "Dieren",
  "DTC": "Doetinchem",
  "DTCH": "Doetinchem De Huet",
  "DDR": "Dordrecht",
  "DDRS": "Dordrecht Stadspolders",
  "DDZD": "Dordrecht Zuid",
  "DB": "Driebergen-Zeist",
  "DRH": "Driehuis",
  "DRP": "Dronrijp",
  "DRON": "Dronten",
  "DVN": "Duiven",
  "DVD": "Duivendrecht",
  "EC": "Echt",
  "EDC": "Ede Centrum",
  "ED": "Ede-Wageningen",
  "WTM": "Eijs-Wittem",
  "EDN": "Eijsden",
  "EHV": "Eindhoven",
  "EHB": "Eindhoven Beukenlaan",
  "EHST": "Eindhoven Stadion",
  "EST": "Elst",
  "EMN": "Emmen",
  "EMNZ": "Emmen Zuid",
  "EKZ": "Enkhuizen",
  "ES": "Enschede",
  "ESE": "Enschede De Eschmarke",
  "ESD": "Enschede Drienerlo",
  "EML": "Ermelo",
  "ETN": "Etten-Leur",
  "EGH": "Eygelshoven",
  "EGHM": "Eygelshoven Markt",
  "FN": "Franeker",
  "GDR": "Gaanderen",
  "GDK": "Geerdijk",
  "GDM": "Geldermalsen",
  "GP": "Geldrop",
  "GLN": "Geleen Oost",
  "LUT": "Geleen-Lutterade",
  "GZ": "Gilze-Rijen",
  "GBR": "Glanerbrug",
  "GS": "Goes",
  "GO": "Goor",
  "GR": "Gorinchem",
  "GD": "Gouda",
  "GDG": "Gouda Goverwelle",
  "GBG": "Gramsbergen",
  "GK": "Grijpskerk",
  "GN": "Groningen",
  "GERP": "Groningen Europapark",
  "GNN": "Groningen Noord",
  "GW": "Grou-Jirnsum",
  "WIJ": "Gulpen-Wijlre",
  "HLM": "Haarlem",
  "HLMS": "Haarlem Spaarnwoude",
  "HWZB": "Halfweg-Zwanenburg",
  "HDB": "Hardenberg",
  "HD": "Harderwijk",
  "HBZM": "Hardinxveld Blauwe Zoom",
  "GND": "Hardinxveld-Giessendam",
  "HRN": "Haren",
  "HLG": "Harlingen",
  "HLGH": "Harlingen Haven",
  "HK": "Heemskerk",
  "HAD": "Heemstede-Aerdenhout",
  "HR": "Heerenveen",
  "HRY": "Heerenveen IJsstadion",
  "HWD": "Heerhugowaard",
  "HRL": "Heerlen",
  "HRLK": "Heerlen De Kissel",
  "HRLW": "Heerlen Woonboulevard",
  "HZE": "Heeze",
  "HLO": "Heiloo",
  "HNO": "Heino",
  "HM": "Helmond",
  "HMH": "Helmond 't Hout",
  "HMBV": "Helmond Brandevoort",
  "HMBH": "Helmond Brouwhuis",
  "HMN": "Hemmen-Dodewaard",
  "HGL": "Hengelo",
  "FKB": "Hengelo FBK stadion",
  "HGLG": "Hengelo Gezondheidspark",
  "HGLO": "Hengelo Oost",
  "HIL": "Hillegom",
  "HVS": "Hilversum",
  "HVSN": "Hilversum Noord",
  "HVSP": "Hilversum Sportpark",
  "HNP": "Hindeloopen",
  "HLD": "Hoek van Holland Haven",
  "HLDS": "Hoek van Holland Strand",
  "HB": "Hoensbroek",
  "HVL": "Hoevelaken",
  "HOR": "Hollandsche Rading",
  "HON": "Holten",
  "HFD": "Hoofddorp",
  "HGV": "Hoogeveen",
  "HGZ": "Hoogezand-Sappemeer",
  "HKS": "Hoogkarspel",
  "HN": "Hoorn",
  "HNK": "Hoorn Kersenboogerd",
  "HRT": "Horst-Sevenum",
  "HTN": "Houten",
  "HTNC": "Houten Castellum",
  "SGL": "Houthem-St Gerlach",
  "HDG": "Hurdegaryp",
  "IJT": "IJlst",
  "KPN": "Kampen",
  "KPNZ": "Kampen Zuid",
  "BZL": "Kapelle-Biezelinge",
  "KRD": "Kerkrade Centrum",
  "KRW": "Kerkrade West",
  "KTR": "Kesteren",
  "KBK": "Klarenbeek",
  "KMR": "Klimmen-Ransdaal",
  "KBW": "Koog Bloemwijk",
  "KZD": "Koog-Zaandijk",
  "KMW": "Koudum-Molkwerum",
  "KBD": "Krabbendijke",
  "KMA": "Krommenie-Assendelft",
  "KW": "Kropswolde",
  "KRG": "Kruiningen-Yerseke",
  "ZLW": "Lage Zwaluwe",
  "LG": "Landgraaf",
  "LDM": "Leerdam",
  "LW": "Leeuwarden",
  "ADH": "Leeuwarden Achter d Hoven",
  "LWC": "Leeuwarden Camminghaburen",
  "LEDN": "Leiden Centraal",
  "LDL": "Leiden Lammenschans",
  "LLS": "Lelystad Centrum",
  "LTV": "Lichtenvoorde-Groenlo",
  "LC": "Lochem",
  "LP": "Loppersum",
  "LTN": "Lunteren",
  "MZ": "Maarheeze",
  "MRN": "Maarn",
  "MAS": "Maarssen",
  "MSS": "Maassluis",
  "MSW": "Maassluis West",
  "MT": "Maastricht",
  "MTR": "Maastricht Randwyck",
  "MG": "Mantgum",
  "MRB": "Mariënberg",
  "MTH": "Martenshoek",
  "MES": "Meerssen",
  "MP": "Meppel",
  "MDB": "Middelburg",
  "MMLH": "Mook Molenhoek",
  "NDB": "Naarden-Bussum",
  "NA": "Nieuw Amsterdam",
  "NVP": "Nieuw Vennep",
  "NWK": "Nieuwerkerk a/d IJssel",
  "NSCH": "Nieuweschans",
  "NKK": "Nijkerk",
  "NM": "Nijmegen",
  "NMD": "Nijmegen Dukenburg",
  "NMH": "Nijmegen Heyendaal",
  "NML": "Nijmegen Lent",
  "NVD": "Nijverdal",
  "NS": "Nunspeet",
  "NH": "Nuth",
  "OBD": "Obdam",
  "OT": "Oisterwijk",
  "ODZ": "Oldenzaal",
  "OST": "Olst",
  "OMN": "Ommen",
  "OLV": "Onze Lieve Vrouwe t. Nood",
  "OTB": "Oosterbeek",
  "OP": "Opheusden",
  "O": "Oss",
  "OW": "Oss West",
  "ODB": "Oudenbosch",
  "OVN": "Overveen",
  "PMR": "Purmerend",
  "PMO": "Purmerend Overwhere",
  "PMW": "Purmerend Weidevenne",
  "PT": "Putten",
  "RAT": "Raalte",
  "RVS": "Ravenstein",
  "RV": "Reuver",
  "RH": "Rheden",
  "RHN": "Rhenen",
  "RSN": "Rijssen",
  "RSW": "Rijswijk",
  "RB": "Rilland-Bath",
  "RM": "Roermond",
  "RD": "Roodeschool",
  "RSD": "Roosendaal",
  "RS": "Rosmalen",
  "RTA": "Rotterdam Alexander",
  "RTB": "Rotterdam Blaak",
  "RTD": "Rotterdam Centraal",
  "RLB": "Rotterdam Lombardijen",
  "RTN": "Rotterdam Noord",
  "RTST": "Rotterdam Stadion",
  "RTZ": "Rotterdam Zuid",
  "RTDZPL": "Rotterdam Zuidplein",
  "RL": "Ruurlo",
  "SPTN": "Santpoort Noord",
  "SPTZ": "Santpoort Zuid",
  "SPM": "Sappemeer Oost",
  "SSH": "Sassenheim",
  "SWD": "Sauwerd",
  "SGN": "Schagen",
  "SDA": "Scheemda",
  "SDM": "Schiedam Centrum",
  "NWL": "Schiedam Nieuwland",
  "SOG": "Schin op Geul",
  "SN": "Schinnen",
  "SHL": "Schiphol",
  "SPV": "Simpelveld",
  "STD": "Sittard",
  "SDT": "Sliedrecht",
  "SDTB": "Sliedrecht Baanhoek",
  "SK": "Sneek",
  "SKND": "Sneek Noord",
  "ST": "Soest",
  "STZ": "Soest Zuid",
  "SD": "Soestdijk",
  "SBK": "Spaubeek",
  "SPH": "Spekholzerheide",
  "STV": "Stavoren",
  "STM": "Stedum",
  "SWK": "Steenwijk",
  "SRN": "Susteren",
  "SM": "Swalmen",
  "TG": "Tegelen",
  "TBG": "Terborg",
  "TL": "Tiel",
  "TPSW": "Tiel Passewaaij",
  "TB": "Tilburg",
  "TBR": "Tilburg Reeshof",
  "TBU": "Tilburg Universiteit",
  "TWL": "Twello",
  "UTG": "Uitgeest",
  "UHZ": "Uithuizen",
  "UHM": "Uithuizermeeden",
  "UST": "Usquert",
  "UT": "Utrecht Centraal",
  "UTLR": "Utrecht Leidsche Rijn",
  "UTL": "Utrecht Lunetten",
  "UTM": "Utrecht Maliebaan",
  "UTO": "Utrecht Overvecht",
  "UTT": "Utrecht Terwijde",
  "UTWR": "Utrecht Westraven",
  "UTZL": "Utrecht Zuilen",
  "VK": "Valkenburg",
  "VMW": "Van der Madeweg",
  "VSV": "Varsseveld",
  "VDM": "Veendam",
  "VNDC": "Veenendaal Centrum",
  "VNDW": "Veenendaal West",
  "KLP": "Veenendaal-De Klomp",
  "VWD": "Veenwouden",
  "VP": "Velp",
  "VL": "Venlo",
  "VRY": "Venray",
  "VLB": "Vierlingsbeek",
  "VDG": "Vlaardingen Centrum",
  "VDO": "Vlaardingen Oost",
  "VDW": "Vlaardingen West",
  "VTN": "Vleuten",
  "VS": "Vlissingen",
  "VSS": "Vlissingen Souburg",
  "VDL": "Voerendaal",
  "VB": "Voorburg",
  "VH": "Voorhout",
  "VST": "Voorschoten",
  "VEM": "Voorst-Empe",
  "VD": "Vorden",
  "VZ": "Vriezenveen",
  "VHP": "Vroomshoop",
  "VG": "Vught",
  "WAD": "Waddinxveen",
  "WADN": "Waddinxveen Noord",
  "WFM": "Warffum",
  "WT": "Weert",
  "WP": "Weesp",
  "WL": "Wehl",
  "WTV": "Westervoort",
  "WZ": "Wezep",
  "WDN": "Wierden",
  "WC": "Wijchen",
  "WH": "Wijhe",
  "WS": "Winschoten",
  "WSM": "Winsum",
  "WW": "Winterswijk",
  "WWW": "Winterswijk West",
  "WD": "Woerden",
  "WF": "Wolfheze",
  "WV": "Wolvega",
  "WK": "Workum",
  "WM": "Wormerveer",
  "ZD": "Zaandam",
  "ZDK": "Zaandam Kogerveld",
  "ZBM": "Zaltbommel",
  "ZVT": "Zandvoort aan Zee",
  "ZA": "Zetten-Andelst",
  "ZV": "Zevenaar",
  "ZVB": "Zevenbergen",
  "ZTM": "Zoetermeer",
  "ZTMO": "Zoetermeer Oost",
  "ZB": "Zuidbroek",
  "ZH": "Zuidhorn",
  "ZP": "Zutphen",
  "ZWW": "Zwaagwesteinde",
  "ZWD": "Zwijndrecht",
  "ZL": "Zwolle"
}